digiseller/__init__.py
digiseller/digiseller.py
digiseller/validators.py
digiseller/api/__init__.py
digiseller/api/general.py
digiseller/api/operations.py
digiseller/api/products.py
digiseller/api/statistics.py
digiseller-0.0.6.dist-info/METADATA
digiseller-0.0.6.dist-info/WHEEL
digiseller-0.0.6.dist-info/top_level.txt
digiseller-0.0.6.dist-info/RECORD
